rdbtools/__init__.py
rdbtools/callbacks.py
rdbtools/compat.py
rdbtools/encodehelpers.py
rdbtools/iowrapper.py
rdbtools/memprofiler.py
rdbtools/parser.py
rdbtools/cli/__init__.py
rdbtools/cli/rdb.py
rdbtools/cli/redis_memory_for_key.py
rdbtools/cli/redis_profiler.py
rdbtools/templates/report.html.template
rdb_cli-0.2.0.dist-info/LICENSE
rdb_cli-0.2.0.dist-info/METADATA
rdb_cli-0.2.0.dist-info/WHEEL
rdb_cli-0.2.0.dist-info/entry_points.txt
rdb_cli-0.2.0.dist-info/top_level.txt
rdb_cli-0.2.0.dist-info/RECORD
