Metadata-Version: 2.1
Name: rdb-cli
Version: 0.2.0
Summary: Utilities to convert Redis RDB files to JSON or SQL formats
Home-page: https://github.com/sripathikrishnan/redis-rdb-tools
Download-URL: https://github.com/sripathikrishnan/redis-rdb-tools/archive/rdbtools-0.2.0.tar.gz
Author: Sripathi Krishnan, Redis Labs
Author-email: Sripathi.Krishnan@gmail.com
Maintainer: Sripathi Krishnan, Redis Labs
Maintainer-email: oss@redislabs.com
License: MIT
Keywords: Redis,RDB,Export,Dump,Memory Profiler
Classifier: Development Status :: 5 - Production/Stable
Classifier: Environment :: Console
Classifier: Intended Audience :: Developers
Classifier: License :: OSI Approved :: MIT License
Classifier: Operating System :: OS Independent
Classifier: Programming Language :: Python
License-File: LICENSE
